README.md
setup.cfg
setup.py
abstract_turtle/__init__.py
abstract_turtle/canvas.py
abstract_turtle/color_names.py
abstract_turtle/forwarding_canvas.py
abstract_turtle/logging_canvas.py
abstract_turtle/model.py
abstract_turtle/pillow_canvas.py
abstract_turtle/tk_canvas.py
abstract_turtle/turtle.py
abstract_turtle/turtle_class.py
abstract_turtle.egg-info/PKG-INFO
abstract_turtle.egg-info/SOURCES.txt
abstract_turtle.egg-info/dependency_links.txt
abstract_turtle.egg-info/requires.txt
abstract_turtle.egg-info/top_level.txt
tests/__init__.py
tests/basic_tests.py
tests/image_tests.py
tests/tk_smoke_test.py
tests/turtle_module_tests.py
tests/utils.py